Workbook

Sheet Dashboard
A1: COMMODITIES & CURRENCY MARKETS — Interactive Dashboard
B4: Select commodity: | D4: Silver | F4: ◄ click the cell, then pick from the dropdown
A6: LATEST PRICE (USD) | D6: VS LONG-TERM AVG | G6: ALL-TIME HIGH | J6: ALL-TIME LOW
A7: =INDEX(KPI_Calc!$B$2:$B$4,MATCH(Dashboard!$D$4,KPI_Calc!$A$2:$A$4,0)) -> 88.36 | D7: =INDEX(KPI_Calc!$D$2:$D$4,MATCH(Dashboard!$D$4,KPI_Calc!$A$2:$A$4,0)) -> 12.759478 | G7: =INDEX(KPI_Calc!$E$2:$E$4,MATCH(Dashboard!$D$4,KPI_Calc!$A$2:$A$4,0)) -> 113.9528 | J7: =INDEX(KPI_Calc!$G$2:$G$4,MATCH(Dashboard!$D$4,KPI_Calc!$A$2:$A$4,0)) -> 0.28
G9: ="in "&INDEX(KPI_Calc!$F$2:$F$4,MATCH(Dashboard!$D$4,KPI_Calc!$A$2:$A$4,0)) -> in 2026 | J9: ="in "&INDEX(KPI_Calc!$H$2:$H$4,MATCH(Dashboard!$D$4,KPI_Calc!$A$2:$A$4,0)) -> in 1932
A46: MARKET SENSITIVITY TO GLOBAL EVENTS (Monthly Price Volatility)
A47: Market | D47: Volatility (Std Dev) | G47: Max Monthly Move | J47: Sensitivity Rank
A48: Brent Oil | D48: =KPI_Calc!B8 -> 0.090506318 | G48: =KPI_Calc!C8 -> 1.3252191 | J48: =KPI_Calc!D8 -> 1
A49: Silver | D49: =KPI_Calc!B9 -> 0.076948135 | G49: =KPI_Calc!C9 -> 0.69473684 | J49: =KPI_Calc!D9 -> 2
A50: Gold | D50: =KPI_Calc!B10 -> 0.04295571 | G50: =KPI_Calc!C10 -> 0.32225161 | J50: =KPI_Calc!D10 -> 3
A51: Currencies (USD basket) | D51: =KPI_Calc!B11 -> 0.025 | G51: =KPI_Calc!C11 -> 0.1 | J51: =KPI_Calc!D11 -> 4
A52: Brent Oil / Gold / Silver volatility computed live from monthly price data (Data_Monthly). Currency volatility is a fixed benchmark from the project report (not computable from the 3-month SWIFT snapshot).
A72: BRICS+ SHARE OF GLOBAL GOLD RESERVES (2019 → 2026)
A73: Year | D73: Share of Global Gold Reserves
A74: 2019 | D74: =KPI_Calc!B15 -> 0.112
A75: 2026 | D75: =KPI_Calc!B16 -> 0.174
A76: Fixed external benchmark (hardcoded). Source: World Gold Council, Central Bank Gold Demand Report 2025; IMF (2024) COFER. See KPI_Calc for the cell-level source note.
A96: KEY INSIGHTS FOR MANAGEMENT
A97: 1. Oil is the most unpredictable cost in any business that uses energy.
A98: Brent Oil can rise over 130% or fall over 50% in a single month. Companies dependent on energy should maintain a systematic fuel-cost hedging plan (50–70% of projected consumption) to avoid a single geopolitical shock (e.g. a Hormuz-type disruption) destroying margins overnight.
A100: 2. Gold is now a strategic reserve tool, not just a jewellery asset.
A101: BRICS+ central banks lifted their share of global gold reserves from 11.2% (2019) to 17.4% (2026), pushing gold to record prices above ,100/oz. A 5–10% gold allocation offers meaningful protection against currency and geopolitical risk.
A103: 3. The US Dollar still leads world payments — but its grip is slowly loosening.
A104: USD holds 51.14% of SWIFT payment value, down from roughly 56% a decade ago. CNY is quietly rising in trade finance (2nd globally at 8.04%) even while ranking only 10th in overall payments — worth monitoring for Asia-Pacific-facing businesses.
A106: HOW TO USE THIS DASHBOARD
A107: 1. Click cell D4 and choose Brent Oil, Gold or Silver — the KPI cards and the top chart update instantly.
A108: 2. Data lives in Data_Monthly, Data_Annual and Data_Currency (formatted Excel Tables); nothing is hard-typed except two clearly labeled external benchmarks (see cell comments in KPI_Calc).
A109: 3. The Market Sensitivity and BRICS+ charts are always-on (they compare all markets, independent of the D4 selector).
... A111: 5. All KPI figures are live formulas (see KPI_Calc) and will recalculate if the underlying datasets are updated.

Sheet Data_Monthly
A1: Date | B1: Year | C1: Month | D1: MonthName | E1: Commodity | F1: Price | G1: MoM % Change
A2: 16803 | B2: 1946 | C2: 1 | D2: Jan | E2: Brent Oil | F2: 21.23
A3: 16834 | B3: 1946 | C3: 2 | D3: Feb | E3: Brent Oil | F3: 21.35 | G3: =IF(E3=E2,F3/F2-1,"") -> 0.0056523787
A4: 16862 | B4: 1946 | C4: 3 | D4: Mar | E4: Brent Oil | F4: 21.11 | G4: =IF(E4=E3,F4/F3-1,"") -> -0.011241218
A5: 16893 | B5: 1946 | C5: 4 | D5: Apr | E5: Brent Oil | F5: 22.79 | G5: =IF(E5=E4,F5/F4-1,"") -> 0.079583136
A6: 16923 | B6: 1946 | C6: 5 | D6: May | E6: Brent Oil | F6: 22.67 | G6: =IF(E6=E5,F6/F5-1,"") -> -0.0052654673
A7: 16954 | B7: 1946 | C7: 6 | D7: Jun | E7: Brent Oil | F7: 22.43 | G7: =IF(E7=E6,F7/F6-1,"") -> -0.010586678
A8: 16984 | B8: 1946 | C8: 7 | D8: Jul | E8: Brent Oil | F8: 21.18 | G8: =IF(E8=E7,F8/F7-1,"") -> -0.055728934
A9: 17015 | B9: 1946 | C9: 8 | D9: Aug | E9: Brent Oil | F9: 24.85 | G9: =IF(E9=E8,F9/F8-1,"") -> 0.17327668
A10: 17046 | B10: 1946 | C10: 9 | D10: Sep | E10: Brent Oil | F10: 24.6 | G10: =IF(E10=E9,F10/F9-1,"") -> -0.010060362
A11: 17076 | B11: 1946 | C11: 10 | D11: Oct | E11: Brent Oil | F11: 24.13 | G11: =IF(E11=E10,F11/F10-1,"") -> -0.019105691
A12: 17107 | B12: 1946 | C12: 11 | D12: Nov | E12: Brent Oil | F12: 23.56 | G12: =IF(E12=E11,F12/F11-1,"") -> -0.023622047
A13: 17137 | B13: 1946 | C13: 12 | D13: Dec | E13: Brent Oil | F13: 24.88 | G13: =IF(E13=E12,F13/F12-1,"") -> 0.056027165
A14: 17168 | B14: 1947 | C14: 1 | D14: Jan | E14: Brent Oil | F14: 24.88 | G14: =IF(E14=E13,F14/F13-1,"") -> 0
... A3636: 46113 | B3636: 2026 | C3636: 4 | D3636: Apr | E3636: Silver | F3636: 88.36 | G3636: =IF(E3636=E3635,F3636/F3635-1,"") -> 0

Sheet Data_Annual
A1: Year | B1: Brent Oil | C1: Gold | D1: Silver | E1: Selected
A2: 1915 | C2: 19.25 | D2: 0.51 | E2: =INDEX($B2:$D2,MATCH(Dashboard!$D$4,$B$1:$D$1,0)) -> 0.51
A3: 1916 | C3: 19.47 | D3: 0.67 | E3: =INDEX($B3:$D3,MATCH(Dashboard!$D$4,$B$1:$D$1,0)) -> 0.67
A4: 1917 | C4: 19.66 | D4: 0.84 | E4: =INDEX($B4:$D4,MATCH(Dashboard!$D$4,$B$1:$D$1,0)) -> 0.84
A5: 1918 | C5: 19.84 | D5: 0.98 | E5: =INDEX($B5:$D5,MATCH(Dashboard!$D$4,$B$1:$D$1,0)) -> 0.98
A6: 1919 | C6: 20.03 | D6: 1.13 | E6: =INDEX($B6:$D6,MATCH(Dashboard!$D$4,$B$1:$D$1,0)) -> 1.13
A7: 1920 | C7: 20.63 | D7: 1.03 | E7: =INDEX($B7:$D7,MATCH(Dashboard!$D$4,$B$1:$D$1,0)) -> 1.03
A8: 1921 | C8: 20.69 | D8: 0.63 | E8: =INDEX($B8:$D8,MATCH(Dashboard!$D$4,$B$1:$D$1,0)) -> 0.63
A9: 1922 | C9: 20.84 | D9: 0.68 | E9: =INDEX($B9:$D9,MATCH(Dashboard!$D$4,$B$1:$D$1,0)) -> 0.68
A10: 1923 | C10: 20.75 | D10: 0.65 | E10: =INDEX($B10:$D10,MATCH(Dashboard!$D$4,$B$1:$D$1,0)) -> 0.65
A11: 1924 | C11: 20.78 | D11: 0.67 | E11: =INDEX($B11:$D11,MATCH(Dashboard!$D$4,$B$1:$D$1,0)) -> 0.67
A12: 1925 | C12: 20.75 | D12: 0.69 | E12: =INDEX($B12:$D12,MATCH(Dashboard!$D$4,$B$1:$D$1,0)) -> 0.69
A13: 1926 | C13: 20.72 | D13: 0.62 | E13: =INDEX($B13:$D13,MATCH(Dashboard!$D$4,$B$1:$D$1,0)) -> 0.62
... A32: 1945 | C32: 35 | D32: 0.52 | E32: =INDEX($B32:$D32,MATCH(Dashboard!$D$4,$B$1:$D$1,0)) -> 0.52
A33: 1946 | B33: 22.9 | C33: 35 | D33: 0.8 | E33: =INDEX($B33:$D33,MATCH(Dashboard!$D$4,$B$1:$D$1,0)) -> 0.8
A34: 1947 | B34: 27.2 | C34: 35 | D34: 0.72 | E34: =INDEX($B34:$D34,MATCH(Dashboard!$D$4,$B$1:$D$1,0)) -> 0.72
A35: 1948 | B35: 35.31 | C35: 35 | D35: 0.74 | E35: =INDEX($B35:$D35,MATCH(Dashboard!$D$4,$B$1:$D$1,0)) -> 0.74
A36: 1949 | B36: 35.65 | C36: 31.88 | D36: 0.72 | E36: =INDEX($B36:$D36,MATCH(Dashboard!$D$4,$B$1:$D$1,0)) -> 0.72
A37: 1950 | B37: 35.28 | C37: 35 | D37: 0.74 | E37: =INDEX($B37:$D37,MATCH(Dashboard!$D$4,$B$1:$D$1,0)) -> 0.74
A38: 1951 | B38: 32.7 | C38: 35 | D38: 0.89 | E38: =INDEX($B38:$D38,MATCH(Dashboard!$D$4,$B$1:$D$1,0)) -> 0.89
A39: 1952 | B39: 31.96 | C39: 34.69 | D39: 0.85 | E39: =INDEX($B39:$D39,MATCH(Dashboard!$D$4,$B$1:$D$1,0)) -> 0.85
A40: 1953 | B40: 33.5 | C40: 35 | D40: 0.85 | E40: =INDEX($B40:$D40,MATCH(Dashboard!$D$4,$B$1:$D$1,0)) -> 0.85
A41: 1954 | B41: 34.68 | C41: 35.31 | D41: 0.85 | E41: =INDEX($B41:$D41,MATCH(Dashboard!$D$4,$B$1:$D$1,0)) -> 0.85
A42: 1955 | B42: 34.78 | C42: 35.31 | D42: 0.89 | E42: =INDEX($B42:$D42,MATCH(Dashboard!$D$4,$B$1:$D$1,0)) -> 0.89
A43: 1956 | B43: 34.26 | C43: 35.31 | D43: 0.92 | E43: =INDEX($B43:$D43,MATCH(Dashboard!$D$4,$B$1:$D$1,0)) -> 0.92
A44: 1957 | B44: 35.78 | C44: 35 | D44: 0.92 | E44: =INDEX($B44:$D44,MATCH(Dashboard!$D$4,$B$1:$D$1,0)) -> 0.92
... A113: 2026 | B113: 78.67 | C113: 4881.62 | D113: 96.08 | E113: =INDEX($B113:$D113,MATCH(Dashboard!$D$4,$B$1:$D$1,0)) -> 96.08

Sheet Data_Currency
A1: Rank | B1: Currency | C1: GlobalPaymentShare
A2: 1 | B2: USD | C2: 51.14
A3: 2 | B3: EUR | C3: 21.3
A4: 3 | B4: GBP | C4: 6.54
A5: 4 | B5: JPY | C5: 3.53
A6: 5 | B6: CNY | C6: 3.1
A7: 6 | B7: CAD | C7: 3.03
A8: 7 | B8: HKD | C8: 1.76
A9: 8 | B9: AUD | C9: 1.61
A10: 9 | B10: SGD | C10: 1.23
A11: 10 | B11: CHF | C11: 1.07

Sheet KPI_Calc
A1: Commodity | B1: Latest | C1: LongTermAvg | D1: VsAvgPct | E1: AllTimeHigh | F1: HighYear | G1: AllTimeLow | H1: LowYear | I1: MaxDate
A2: Brent Oil | B2: =SUMIFS(Data_Monthly!$F$2:$F$3636,Data_Monthly!$E$2:$E$3636,$A2,Data_Monthly!$A$2:$A$3636,$I2) -> 102.86 | C2: =AVERAGEIFS(Data_Monthly!$F$2:$F$3636,Data_Monthly!$E$2:$E$3636,$A2) -> 62.70947 | D2: =B2/C2-1 -> 0.64026262 | E2: =_xlfn.MAXIFS(Data_Monthly!$F$2:$F$3636,Data_Monthly!$E$2:$E$3636,$A2) -> 211.21 | F2: =_xlfn.MINIFS(Data_Monthly!$B$2:$B$3636,Data_Monthly!$E$2:$E$3636,$A2,Data_Monthly!$F$2:$F$3636,E2) -> 2008 | G2: =_xlfn.MINIFS(Data_Monthly!$F$2:$F$3636,Data_Monthly!$E$2:$E$3636,$A2) -> 21.11 | H2: =_xlfn.MINIFS(Data_Monthly!$B$2:$B$3636,Data_Monthly!$E$2:$E$3636,$A2,Data_Monthly!$F$2:$F$3636,G2) -> 1946 | I2: =_xlfn.MAXIFS(Data_Monthly!$A$2:$A$3636,Data_Monthly!$E$2:$E$3636,$A2) -> 46082
A3: Gold | B3: =SUMIFS(Data_Monthly!$F$2:$F$3636,Data_Monthly!$E$2:$E$3636,$A3,Data_Monthly!$A$2:$A$3636,$I3) -> 4712.8906 | C3: =AVERAGEIFS(Data_Monthly!$F$2:$F$3636,Data_Monthly!$E$2:$E$3636,$A3) -> 397.55139 | D3: =B3/C3-1 -> 10.854796 | E3: =_xlfn.MAXIFS(Data_Monthly!$F$2:$F$3636,Data_Monthly!$E$2:$E$3636,$A3) -> 5277.89 | F3: =_xlfn.MINIFS(Data_Monthly!$B$2:$B$3636,Data_Monthly!$E$2:$E$3636,$A3,Data_Monthly!$F$2:$F$3636,E3) -> 2026 | G3: =_xlfn.MINIFS(Data_Monthly!$F$2:$F$3636,Data_Monthly!$E$2:$E$3636,$A3) -> 19.25 | H3: =_xlfn.MINIFS(Data_Monthly!$B$2:$B$3636,Data_Monthly!$E$2:$E$3636,$A3,Data_Monthly!$F$2:$F$3636,G3) -> 1915 | I3: =_xlfn.MAXIFS(Data_Monthly!$A$2:$A$3636,Data_Monthly!$E$2:$E$3636,$A3) -> 46113
A4: Silver | B4: =SUMIFS(Data_Monthly!$F$2:$F$3636,Data_Monthly!$E$2:$E$3636,$A4,Data_Monthly!$A$2:$A$3636,$I4) -> 88.36 | C4: =AVERAGEIFS(Data_Monthly!$F$2:$F$3636,Data_Monthly!$E$2:$E$3636,$A4) -> 6.4217552 | D4: =B4/C4-1 -> 12.759478 | E4: =_xlfn.MAXIFS(Data_Monthly!$F$2:$F$3636,Data_Monthly!$E$2:$E$3636,$A4) -> 113.9528 | F4: =_xlfn.MINIFS(Data_Monthly!$B$2:$B$3636,Data_Monthly!$E$2:$E$3636,$A4,Data_Monthly!$F$2:$F$3636,E4) -> 2026 | G4: =_xlfn.MINIFS(Data_Monthly!$F$2:$F$3636,Data_Monthly!$E$2:$E$3636,$A4) -> 0.28 | H4: =_xlfn.MINIFS(Data_Monthly!$B$2:$B$3636,Data_Monthly!$E$2:$E$3636,$A4,Data_Monthly!$F$2:$F$3636,G4) -> 1932 | I4: =_xlfn.MAXIFS(Data_Monthly!$A$2:$A$3636,Data_Monthly!$E$2:$E$3636,$A4) -> 46113
A6: MARKET SENSITIVITY TO GLOBAL EVENTS (MONTHLY VOLATILITY)
A7: Market | B7: Volatility (Std Dev) | C7: Max Monthly Move | D7: Sensitivity Rank
A8: Brent Oil | B8: =STDEV(Data_Monthly!G3:G964) -> 0.090506318 | C8: =MAX(Data_Monthly!G3:G964) -> 1.3252191 | D8: =RANK(B8,$B$8:$B$11,0) -> 1
A9: Silver | B9: =STDEV(Data_Monthly!G2302:G3636) -> 0.076948135 | C9: =MAX(Data_Monthly!G2302:G3636) -> 0.69473684 | D9: =RANK(B9,$B$8:$B$11,0) -> 2
A10: Gold | B10: =STDEV(Data_Monthly!G966:G2300) -> 0.04295571 | C10: =MAX(Data_Monthly!G966:G2300) -> 0.32225161 | D10: =RANK(B10,$B$8:$B$11,0) -> 3
A11: Currencies (USD basket) | B11: 0.025 | C11: 0.1 | D11: =RANK(B11,$B$8:$B$11,0) -> 4
A13: BRICS+ SHARE OF GLOBAL GOLD RESERVES
A14: Year | B14: Share of Global Gold Reserves
A15: 2019 | B15: 0.112
A16: 2026 | B16: 0.174
